[
  {
    "tag_name": "entity",
    "ids_to_tags": {
      "1": "B-first_city",
      "2": "I-first_city",
      "3": "L-first_city",
      "4": "U-first_city",
      "5": "B-second_city",
      "6": "I-second_city",
      "7": "L-second_city",
      "8": "U-second_city",
      "0": "O"
    },
    "tags_to_ids": {
      "B-first_city": 1,
      "I-first_city": 2,
      "L-first_city": 3,
      "U-first_city": 4,
      "B-second_city": 5,
      "I-second_city": 6,
      "L-second_city": 7,
      "U-second_city": 8,
      "O": 0
    },
    "num_tags": 9
  }
]